{"mc":{
	"/Users/coman/Desktop/ybtt/resource/assets/ani/ani_avatar_1134":{
		"frameRate":24,
		"labels":[
			{"name":"idle","frame":1}
			,{"name":"move","frame":2}
			,{"name":"moveEnd","frame":13}
			,{"name":"atk","frame":14}
			,{"name":"atkFire","frame":20}
			,{"name":"atkEnd","frame":28}
			,{"name":"die","frame":29}
			,{"name":"dieEnd","frame":40}
			
			],
		"frames":[
			
			{
			"res":"E5B45D87",
			"x":0,
			"y":0
			},
			{
			"res":"249F6CC1",
			"x":0,
			"y":0,
			"duration":6
			},
			{
			"res":"67D81764",
			"x":0,
			"y":0,
			"duration":3
			},
			{
			"res":"47C98A09",
			"x":0,
			"y":0,
			"duration":3
			},
			{
			"res":"92B45214",
			"x":0,
			"y":0,
			"duration":3
			},
			{
			"res":"ED9771A4",
			"x":0,
			"y":0,
			"duration":9
			},
			{
			"res":"EA8007BB",
			"x":0,
			"y":0,
			"duration":3
			},
			{
			"res":"7A9BFC82",
			"x":0,
			"y":0,
			"duration":6
			},
			{
			"res":"AD330B88",
			"x":0,
			"y":0,
			"duration":3
			},
			{
			"res":"EB58D272",
			"x":0,
			"y":0,
			"duration":5
			}
			]
}},
	"res":{
		"E5B45D87":{"x":1,"y":1,"w":80,"h":70},
		"249F6CC1":{"x":83,"y":1,"w":80,"h":70},
		"67D81764":{"x":165,"y":1,"w":80,"h":70},
		"47C98A09":{"x":1,"y":73,"w":80,"h":70},
		"92B45214":{"x":83,"y":73,"w":80,"h":70},
		"ED9771A4":{"x":165,"y":73,"w":80,"h":70},
		"EA8007BB":{"x":1,"y":145,"w":80,"h":70},
		"7A9BFC82":{"x":83,"y":145,"w":80,"h":70},
		"AD330B88":{"x":165,"y":145,"w":80,"h":70},
		"EB58D272":{"x":1,"y":217,"w":80,"h":70}
	}}